swaggerjmx/__init__.py
swaggerjmx/cli.py
swaggerjmx/convert.py
swaggerjmx/get_swagger.py
swaggerjmx/settings.py
swaggerjmx/to_jmx.py
swaggerjmx/version.py
swaggerjmx-1.1.1.dist-info/LICENSE
swaggerjmx-1.1.1.dist-info/METADATA
swaggerjmx-1.1.1.dist-info/WHEEL
swaggerjmx-1.1.1.dist-info/entry_points.txt
swaggerjmx-1.1.1.dist-info/top_level.txt
swaggerjmx-1.1.1.dist-info/RECORD
