Metadata-Version: 2.1
Name: swaggerjmx
Version: 1.1.1
Summary: swagger convert jmx
Home-page: https://github.com/Pactortester/swaggerjmx
Author: lijiawei
Author-email: 1456470136@qq.com
License: MIT Licence
Keywords: pip,swagger,jmx,yapi,swaggerjmx,jmeter,swagger convert jmx
Platform: any
Classifier: License :: OSI Approved :: MIT License
Classifier: Development Status :: 5 - Production/Stable
Classifier: Environment :: Console :: Curses
Classifier: Operating System :: MacOS
Classifier: Operating System :: POSIX
Classifier: Operating System :: Microsoft :: Windows
Classifier: Programming Language :: Python :: 3 :: Only
Classifier: Programming Language :: Python :: 3.6
Classifier: Programming Language :: Python :: 3.7
Classifier: Programming Language :: Python :: 3.8
Classifier: Programming Language :: Python :: Implementation :: CPython
Classifier: Topic :: Security
Classifier: Topic :: Internet :: WWW/HTTP
Classifier: Topic :: Software Development :: Testing
Classifier: Typing :: Typed
License-File: LICENSE
Requires-Dist: lxml
Requires-Dist: requests
Requires-Dist: loguru
